{
  "type": "minecraft:block",
  "pools": [
    {
      "rolls": 1,
      "entries": [
        {
          "type": "minecraft:item",
          "name": "minecraft:prismarine_shard",
          "weight": 60,
          "functions": [
            {
              "function": "minecraft:set_count",
              "count": {
                "min": 2,
                "max": 4
              }
            }
          ]
        },
        {
          "type": "minecraft:item",
          "name": "minecraft:prismarine_crystals",
          "weight": 30,
          "functions": [
            {
              "function": "minecraft:set_count",
              "count": {
                "min": 2,
                "max": 4
              }
            }
          ]
        },
        {
          "type": "minecraft:loot_table",
          "name": "skyworld:diamond",
          "weight": 10
        }
      ]
    }
  ]
}