{
  "pools": [
    {
      "rolls": 1,
      "entries": [
        {
          "type": "minecraft:alternatives",
          "children": [
            {
              "type": "minecraft:loot_table",
              "name": "looting:drops/player/stone",
              "functions": [],
              "conditions": [
                {
                  "condition": "minecraft:entity_properties",
                  "entity": "this",
                  "predicate": {
                    "type": "minecraft:player"
                  }
                }
              ]
            },
            {
              "type": "minecraft:loot_table",
              "name": "looting:drops/other/stone"
            }
          ]
        }
      ],
      "functions": []
    }
  ]
}